.gitignore
LICENSE
README.md
requirements.txt
setup.py
figures/workflow.jpg
scripts/run.sh
scripts/test_tcr2vec.py
tcr2vec/__init__.py
tcr2vec/cdr3_to_full_seq.py
tcr2vec/dataset.py
tcr2vec/embed.py
tcr2vec/evaluate.py
tcr2vec/finetune.py
tcr2vec/model.py
tcr2vec/predict.py
tcr2vec/utils.py
tcr2vec.egg-info/PKG-INFO
tcr2vec.egg-info/SOURCES.txt
tcr2vec.egg-info/dependency_links.txt
tcr2vec.egg-info/not-zip-safe
tcr2vec.egg-info/requires.txt
tcr2vec.egg-info/top_level.txt
tcr2vec/Epi_model/Atchley_factors.csv
tcr2vec/Epi_model/__init__.py
tcr2vec/Epi_model/aaindex2.txt
tcr2vec/Epi_model/epi_encode_ae.py
tcr2vec/Epi_model/epi_encode_ed.py
tcr2vec/Epi_model/ept_trained_AE.h5
tcr2vec/data/sample.csv
tcr2vec/data/TCR_gene_segment_data/J_segment_sequences.fasta
tcr2vec/data/TCR_gene_segment_data/V_segment_sequences.fasta
tcr2vec/results/sample_full.csv