Metadata-Version: 1.1
Name: tcr2vec
Version: 1.0.1
Summary: TCR2vec is a deep representation learning framework of T-cell receptor sequence and function
Home-page: https://github.com/jiangdada1221/TCR2vec
Author: Yuepeng Jiang
Author-email: jiangdada12344321@gmail.com
License: GPLv3
Platform: UNKNOWN
Classifier: Development Status :: 3 - Alpha
Classifier: Intended Audience :: Developers
Classifier: Intended Audience :: Healthcare Industry
Classifier: Intended Audience :: Science/Research
Classifier: Topic :: Scientific/Engineering :: Bio-Informatics
Classifier: Topic :: Scientific/Engineering :: Artificial Intelligence
Classifier: Topic :: Scientific/Engineering :: Medical Science Apps.
Classifier: License :: OSI Approved :: GNU General Public License v3 (GPLv3)
Classifier: Natural Language :: English
Classifier: Programming Language :: Python :: 3
